document_tracking/__init__.py
document_tracking/clustering.py
document_tracking/evaluation.py
document_tracking/learning.py
document_tracking/similarity.py
document_tracking/kmeans/__init__.py
document_tracking/kmeans/clustering.py
document_tracking/miranda/__init__.py
document_tracking/miranda/clustering.py
document_tracking/miranda/learning.py
document_tracking/miranda/similarity.py
document_tracking/resources/__init__.py
document_tracking/resources/models.py
document_tracking/third_party/__init__.py
document_tracking-1.0.2.202209211710.dist-info/AUTHORS
document_tracking-1.0.2.202209211710.dist-info/LICENSE
document_tracking-1.0.2.202209211710.dist-info/LICENSE_BSD
document_tracking-1.0.2.202209211710.dist-info/METADATA
document_tracking-1.0.2.202209211710.dist-info/WHEEL
document_tracking-1.0.2.202209211710.dist-info/top_level.txt
document_tracking-1.0.2.202209211710.dist-info/RECORD
