Metadata-Version: 2.1
Name: document-tracking
Version: 1.0.2.202209211710
Summary: Algorithms to track documents and build news stories from them. It implements the Miranda et al. (2018) algorithm, as well as other alternatives and baselines to track documents.
Home-page: https://gitlab.univ-lr.fr/cross-lingual-event-tracking/developpement/from-documents-to-events/document_tracking
Author: Guillaume Bernard
Author-email: contact@guillaume-bernard.fr
License: GPLv3 License and 3-Clause BSD Licence
Project-URL: Bug Tracker, https://gitlab.univ-lr.fr/cross-lingual-event-tracking/developpement/from-documents-to-events/document_tracking/-/issues
Platform: UNKNOWN
Classifier: Programming Language :: Python :: 3.9
Classifier: License :: OSI Approved :: GNU General Public License v3 (GPLv3)
Classifier: License :: OSI Approved :: BSD License
Classifier: Topic :: Scientific/Engineering :: Artificial Intelligence
Classifier: Intended Audience :: Science/Research
Classifier: Topic :: Scientific/Engineering :: Information Analysis
Classifier: Operating System :: POSIX :: Linux
Classifier: Intended Audience :: Science/Research
License-File: LICENSE
License-File: LICENSE_BSD
License-File: AUTHORS
Requires-Dist: bcubed (>=1.5)
Requires-Dist: document-tracking-resources (>=1.0.1.202208310822)
Requires-Dist: numpy (>=1.22.0)
Requires-Dist: pandas (>=1.5.0)
Requires-Dist: scikit-learn (>=1.1.2)
Requires-Dist: scipy (>=1.9.1)
Requires-Dist: sentence-transformers (>=2.2.2)
Requires-Dist: setuptools (>=59.6.0)
Requires-Dist: tqdm (>=4.64.1)
Requires-Dist: yellowbrick (>=1.5)
